AUTHORS.rst
CHANGELOG.rst
CONTRIBUTING.rst
LICENSE
MANIFEST.in
README.rst
setup.cfg
setup.py
teamsupport/__init__.py
teamsupport/config.py
teamsupport/errors.py
teamsupport/models.py
teamsupport/services.py
teamsupport.egg-info/PKG-INFO
teamsupport.egg-info/SOURCES.txt
teamsupport.egg-info/dependency_links.txt
teamsupport.egg-info/not-zip-safe
teamsupport.egg-info/requires.txt
teamsupport.egg-info/top_level.txt